svdsuite/__init__.py
svdsuite/_version.py
svdsuite/map.py
svdsuite/parse.py
svdsuite/process.py
svdsuite/py.typed
svdsuite/serialize.py
svdsuite/validate.py
svdsuite/model/__init__.py
svdsuite/model/map.py
svdsuite/model/parse.py
svdsuite/model/process.py
svdsuite/model/type_alias.py
svdsuite/model/types.py
svdsuite/resolve/__init__.py
svdsuite/resolve/exception.py
svdsuite/resolve/graph.py
svdsuite/resolve/graph_builder.py
svdsuite/resolve/graph_elements.py
svdsuite/resolve/logger.py
svdsuite/resolve/resolver.py
svdsuite/schema/1.0.xsd
svdsuite/schema/1.1.xsd
svdsuite/schema/1.2.xsd
svdsuite/schema/1.3.1.xsd
svdsuite/schema/1.3.10.xsd
svdsuite/schema/1.3.11.xsd
svdsuite/schema/1.3.2.xsd
svdsuite/schema/1.3.3.xsd
svdsuite/schema/1.3.4.xsd
svdsuite/schema/1.3.5.xsd
svdsuite/schema/1.3.6.xsd
svdsuite/schema/1.3.7.xsd
svdsuite/schema/1.3.8.xsd
svdsuite/schema/1.3.9.xsd
svdsuite/util/__init__.py
svdsuite/util/html_generator.py
svdsuite/util/parser_exception_warning.py
svdsuite/util/process_parse_model_convert.py
svdsuite/util/xml_parse.py
svdsuite-0.2.2.dist-info/licenses/LICENSE
svdsuite-0.2.2.dist-info/METADATA
svdsuite-0.2.2.dist-info/WHEEL
svdsuite-0.2.2.dist-info/top_level.txt
svdsuite-0.2.2.dist-info/RECORD
