Metadata-Version: 2.4
Name: svdsuite
Version: 0.2.2
Summary: A Python package to parse, process, manipulate, validate, and generate CMSIS SVD files
Author: Christian Kudera
License: MIT License
Project-URL: Documentation, https://github.com/ARMify-Project/SVDSuite?tab=readme-ov-file
Project-URL: Issues, https://github.com/ARMify-Project/SVDSuite/issues
Project-URL: Source, https://github.com/ARMify-Project/SVDSuite
Keywords: CMSIS,SVD,Embedded Systems,ARM,Cortex-M,Microcontroller
Classifier: Development Status :: 4 - Beta
Classifier: Intended Audience :: Science/Research
Classifier: Intended Audience :: Developers
Classifier: License :: OSI Approved :: MIT License
Classifier: Programming Language :: Python
Classifier: Programming Language :: Python :: 3.10
Classifier: Programming Language :: Python :: 3.11
Classifier: Programming Language :: Python :: 3.12
Classifier: Programming Language :: Python :: Implementation :: CPython
Classifier: Programming Language :: Python :: Implementation :: PyPy
Classifier: Topic :: Software Development :: Embedded Systems
Classifier: Topic :: Scientific/Engineering
Classifier: Typing :: Typed
Requires-Python: >=3.10
License-File: LICENSE
Requires-Dist: lxml>=4.9.3
Requires-Dist: rustworkx>=0.15.1
Provides-Extra: dev
Requires-Dist: pytest>=8.1.1; extra == "dev"
Dynamic: license-file
